README.rst
setup.py
w3af_api_client/__init__.py
w3af_api_client/connection.py
w3af_api_client/finding.py
w3af_api_client/log.py
w3af_api_client/scan.py
w3af_api_client/scanner_exception.py
w3af_api_client/traffic.py
w3af_api_client.egg-info/PKG-INFO
w3af_api_client.egg-info/SOURCES.txt
w3af_api_client.egg-info/dependency_links.txt
w3af_api_client.egg-info/requires.txt
w3af_api_client.egg-info/top_level.txt
w3af_api_client/tests/__init__.py
w3af_api_client/tests/base.py
w3af_api_client/tests/test_exceptions.py
w3af_api_client/tests/test_fuzzable_requests.py
w3af_api_client/tests/test_log.py
w3af_api_client/tests/test_query_scans.py
w3af_api_client/tests/test_scan.py
w3af_api_client/tests/test_stop_clear.py
w3af_api_client/tests/test_urls.py
w3af_api_client/tests/utils/__init__.py
w3af_api_client/tests/utils/mock.py
w3af_api_client/utils/__init__.py
w3af_api_client/utils/constants.py
w3af_api_client/utils/details.py
w3af_api_client/utils/exceptions.py
w3af_api_client/utils/stdout_wrapper.py