Metadata-Version: 1.1
Name: w3af-api-client
Version: 1.1.7
Summary: REST API client to consume w3af
Home-page: https://github.com/andresriancho/w3af-api-client/
Author: Andres Riancho
Author-email: andres.riancho@gmail.com
License: GNU General Public License v2 (GPLv2)
Platform: Linux
Classifier: Development Status :: 5 - Production/Stable
Classifier: Intended Audience :: Developers
Classifier: License :: OSI Approved :: GNU General Public License v2 (GPLv2)
Classifier: Natural Language :: English
Classifier: Operating System :: POSIX :: Linux
Classifier: Programming Language :: Python
Classifier: Programming Language :: Python :: 2.7
Classifier: Topic :: System :: Monitoring
